lunchpy/__init__.py
lunchpy/eat.py
lunchpy-1.0.0b1.dist-info/LICENCE
lunchpy-1.0.0b1.dist-info/METADATA
lunchpy-1.0.0b1.dist-info/WHEEL
lunchpy-1.0.0b1.dist-info/top_level.txt
lunchpy-1.0.0b1.dist-info/RECORD
