Metadata-Version: 2.1
Name: lunchpy
Version: 1.0.0b1
Summary: An API wrapper for Lunch Money
Home-page: https://github.com/Vyryn/lunchpy
Author: Vyryn
Author-email: Vyryn@protonmail.com
License: GNU General Public License v3 (GPLv3)
Platform: UNKNOWN
Classifier: Development Status :: 3 - Alpha
Classifier: Intended Audience :: Developers
Classifier: Environment :: Console
Classifier: Operating System :: OS Independent
Classifier: License :: OSI Approved :: GNU General Public License v3 (GPLv3)
Classifier: Programming Language :: Python :: 3.9
License-File: LICENCE
Requires-Dist: requests (~=2.25.1)
